Metadata-Version: 2.4
Name: hammett-washington-sdk
Version: 1.7.6
Summary: Vel corrupti volupt
Author-email: Zelenia Merrill <givonys@mailinator.com>
Project-URL: Documentation, https://testing.com
Requires-Python: >=3.7
License-File: LICENSE
Requires-Dist: apimatic-core>=0.2.20,~=0.2.0
Requires-Dist: apimatic-core-interfaces>=0.1.5,~=0.1.0
Requires-Dist: apimatic-requests-client-adapter>=0.1.6,~=0.1.0
Provides-Extra: testutils
Requires-Dist: pytest>=7.2.2; extra == "testutils"
Dynamic: license-file
